nerva_torch/__init__.py
nerva_torch/activation_functions.py
nerva_torch/datasets.py
nerva_torch/layers.py
nerva_torch/learning_rate.py
nerva_torch/loss_functions.py
nerva_torch/loss_functions_torch.py
nerva_torch/matrix_operations.py
nerva_torch/multilayer_perceptron.py
nerva_torch/optimizers.py
nerva_torch/softmax_functions.py
nerva_torch/training.py
nerva_torch/utilities.py
nerva_torch/weight_initializers.py
nerva_torch-0.9.0.dist-info/licenses/LICENSE
nerva_torch-0.9.0.dist-info/METADATA
nerva_torch-0.9.0.dist-info/WHEEL
nerva_torch-0.9.0.dist-info/top_level.txt
nerva_torch-0.9.0.dist-info/RECORD
