Metadata-Version: 2.4
Name: nerva-torch
Version: 0.9.0
Summary: An implementation of multilayer perceptrons in PyTorch.
Home-page: https://github.com/wiegerw/nerva-torch
Author: Wieger Wesselink
Author-email: j.w.wesselink@tue.nl
Project-URL: Documentation, https://wiegerw.github.io/nerva-torch/
Project-URL: Bug Tracker, https://github.com/wiegerw/nerva-torch/issues
Classifier: Programming Language :: Python :: 3
Classifier: License :: OSI Approved :: Boost Software License 1.0 (BSL-1.0)
Classifier: Operating System :: OS Independent
Requires-Python: >=3.10
License-File: LICENSE
Requires-Dist: numpy>=1.21
Requires-Dist: torch>=1.12
Requires-Dist: torchvision>=0.13
Requires-Dist: scikit-learn>=1.1
Dynamic: license-file
